Metadata-Version: 2.1
Name: PythonPip
Version: 1.0
Summary: first version
Home-page: https://github.com/helmanso123/PythonLib/
Author: Krzysztof Puciłowski
Author-email: 248405@student.pwr.edu.pl
License: MIT
Platform: UNKNOWN
